Workbook

Sheet assets
A1: latitude | B1: longitude | C1: value | D1: deductible | E1: cover | F1: region_id | G1: category_id | H1: impf_ | I1: centr_

Sheet impact_functions
A1: impact_fun_id | B1: intensity | C1: mdd | D1: paa | E1: peril_id | F1: intensity_unit | G1: name
A2: 1 | B2: 0 | C2: 0 | D2: 0 | E2: TC | F2: m/s | G2: Tropical cyclone default
A3: 1 | B3: 5 | C3: 0 | D3: 0 | E3: TC | F3: m/s | G3: Tropical cyclone default
A4: 1 | B4: 10 | C4: 0 | D4: 0 | E4: TC | F4: m/s | G4: Tropical cyclone default
A5: 1 | B5: 15 | C5: 0 | D5: 0 | E5: TC | F5: m/s | G5: Tropical cyclone default
A6: 1 | B6: 20 | C6: 0 | D6: 0 | E6: TC | F6: m/s | G6: Tropical cyclone default
A7: 1 | B7: 25 | C7: 0 | D7: 0 | E7: TC | F7: m/s | G7: Tropical cyclone default
A8: 1 | B8: 30 | C8: 0 | D8: 0 | E8: TC | F8: m/s | G8: Tropical cyclone default
A9: 1 | B9: 35 | C9: 0.0013 | D9: 0.0034 | E9: TC | F9: m/s | G9: Tropical cyclone default
A10: 1 | B10: 40 | C10: 0.0039 | D10: 0.0105 | E10: TC | F10: m/s | G10: Tropical cyclone default
A11: 1 | B11: 45 | C11: 0.0091 | D11: 0.0243 | E11: TC | F11: m/s | G11: Tropical cyclone default
A12: 1 | B12: 50 | C12: 0.0182 | D12: 0.0487 | E12: TC | F12: m/s | G12: Tropical cyclone default
A13: 1 | B13: 55 | C13: 0.0331 | D13: 0.0882 | E13: TC | F13: m/s | G13: Tropical cyclone default
... A291: 1 | B291: 12 | C291: 1 | D291: 1 | E291: RF | F291: m | G291: River flood default

Sheet measures
A1: name | B1: color | C1: cost | D1: hazard intensity impact a | E1: hazard intensity impact b | F1: hazard high frequency cutoff | G1: hazard event set | H1: MDD impact a | I1: MDD impact b | J1: PAA impact a | K1: PAA impact b | L1: damagefunctions map | M1: assets file | N1: Region_ID | O1: risk transfer attachement | P1: risk transfer cover | Q1: risk transfer cost factor | R1: peril_ID | S1: code
A2: adaptation_measures_green_roofs | B2: 0 0.42 0.36 | C2: 20000000 | D2: 1 | E2: 0 | F2: 0 | G2: nil | H2: 0.69 | I2: 0 | J2: 1 | K2: 0 | L2: nil | M2: nil | N2: 0 | O2: 0 | P2: 0 | Q2: 1 | R2: HW | S2: GR
A3: adaptation_measures_trees_planting | B3: 0.01 0.67 0.51 | C3: 31120332 | D3: 1 | E3: 0 | F3: 0 | G3: nil | H3: 0.675 | I3: 0 | J3: 1 | K3: 0 | L3: nil | M3: nil | N3: 0 | O3: 0 | P3: 0 | Q3: 1 | R3: HW | S3: TP
A4: adaptation_measures_green_spaces | B4: 0 0.42 0.36 | C4: 1145000 | D4: 1 | E4: 0 | F4: 0 | G4: nil | H4: 0.39 | I4: -0.05 | J4: 1 | K4: 0 | L4: nil | M4: nil | N4: 0 | O4: 0 | P4: 0 | Q4: 1 | R4: HW | S4: GS
A5: adaptation_measures_green_white_roofs | B5: 0.01 0.67 0.51 | C5: 298778.18 | D5: 1 | E5: 0 | F5: 0 | G5: nil | H5: 0.75 | I5: 0.06 | J5: 1 | K5: 0 | L5: nil | M5: nil | N5: 0 | O5: 0 | P5: 0 | Q5: 1 | R5: HW
A6: adaptation_measures_early_warning_system | B6: 0.93 0.33 0.34 | C6: 22370745 | D6: 1 | E6: 0 | F6: 0 | G6: nil | H6: 0.78 | I6: 0 | J6: 1 | K6: 0 | L6: nil | M6: nil | N6: 0 | O6: 0 | P6: 0 | Q6: 1 | R6: HW | S6: EWS
A7: adaptation_measures_training_on_adaptation_agricultural_practices | B7: 1 0.5 0.4 | C7: 35952983 | D7: 1 | E7: 0 | F7: 0 | G7: nil | H7: 0.75 | I7: 0 | J7: 1 | K7: 0 | L7: nil | M7: nil | N7: 0 | O7: 0 | P7: 0 | Q7: 1 | R7: HW
A8: adaptation_measures_water_saving_cultivation_and_production_practices | B8: 0.09 0.44 0.61 | C8: 34035490 | D8: 1 | E8: 0 | F8: 0 | G8: nil | H8: 0.8 | I8: 0 | J8: 1 | K8: 0 | L8: nil | M8: nil | N8: 0 | O8: 0 | P8: 0 | Q8: 1 | R8: HW
A9: adaptation_measures_research_and_monitoring | B9: 1 0.75 0.6 | C9: 22398708 | D9: 1 | E9: 0 | F9: 0 | G9: nil | H9: 0.67999 | I9: 0.057 | J9: 1 | K9: 0 | L9: nil | M9: nil | N9: 0 | O9: 0 | P9: 0 | Q9: 1 | R9: HW
A10: adaptation_measures_climate_smart_agriculture | B10: 0.38 0.75 0.6 | C10: 1.1313205e+08 | D10: 1 | E10: 0 | F10: 0 | G10: nil | H10: 0.6 | I10: 0 | J10: 1 | K10: 0 | L10: nil | M10: nil | N10: 0 | O10: 0 | P10: 0 | Q10: 1 | R10: HW | S10: CSA
A11: adaptation_measures_green_building_codes | B11: 1 0.89 0.84 | C11: 1.9654297e+08 | D11: 1 | E11: 0 | F11: 0 | G11: nil | H11: 0.55 | I11: 0 | J11: 1 | K11: 0 | L11: nil | M11: nil | N11: 0 | O11: 0 | P11: 0 | Q11: 1 | R11: HW | S11: GBC
A12: adaptation_measures_green_roofs | B12: 0 0.42 0.36 | C12: 3600000 | D12: 1 | E12: 0 | F12: 0 | G12: nil | H12: 0.69 | I12: 0 | J12: 1 | K12: 0 | L12: nil | M12: nil | N12: 0 | O12: 0 | P12: 0 | Q12: 1 | R12: HW | S12: GR
A13: adaptation_measures_trees_planting | B13: 0.01 0.67 0.51 | C13: 5601659.8 | D13: 1 | E13: 0 | F13: 0 | G13: nil | H13: 0.675 | I13: 0 | J13: 1 | K13: 0 | L13: nil | M13: nil | N13: 0 | O13: 0 | P13: 0 | Q13: 1 | R13: HW | S13: TP
A14: adaptation_measures_early_warning_system | B14: 0.93 0.33 0.34 | C14: 4026734.1 | D14: 1 | E14: 0 | F14: 0 | G14: nil | H14: 0.78 | I14: 0 | J14: 1 | K14: 0 | L14: nil | M14: nil | N14: 0 | O14: 0 | P14: 0 | Q14: 1 | R14: HW | S14: EWS
A15: adaptation_measures_green_building_codes | B15: 1 0.89 0.84 | C15: 35377735 | D15: 1 | E15: 0 | F15: 0 | G15: nil | H15: 0.55 | I15: 0 | J15: 1 | K15: 0 | L15: nil | M15: nil | N15: 0 | O15: 0 | P15: 0 | Q15: 1 | R15: HW | S15: GBC
A16: adaptation_measures_wetland_restoration_and_rehabilitation | B16: 0 0.42 0.36 | C16: 3021000 | D16: 1 | E16: 0 | F16: 0 | G16: nil | H16: 0.65 | I16: 0 | J16: 1 | K16: 0 | L16: nil | M16: nil | N16: 0 | O16: 0 | P16: 0 | Q16: 1 | R16: D
A17: adaptation_measures_soil_water_and_pest_management | B17: 0.01 0.67 0.51 | C17: 6616532.7 | D17: 1 | E17: 0 | F17: 0 | G17: nil | H17: 0.6 | I17: 0 | J17: 1 | K17: 0 | L17: nil | M17: nil | N17: 0 | O17: 0 | P17: 0 | Q17: 1 | R17: D
A18: adaptation_measures_legume_seeds_production_and_propagation | B18: 0.38 0.75 0.6 | C18: 3777900 | D18: 1 | E18: 0 | F18: 0 | G18: nil | H18: 0.7 | I18: 0 | J18: 1 | K18: 0 | L18: nil | M18: nil | N18: 0 | O18: 0 | P18: 0 | Q18: 1 | R18: D
A19: adaptation_measures_management_of_protected_environmental_areas | B19: 0.09 0.44 0.61 | C19: 13233065 | D19: 1 | E19: 0 | F19: 0 | G19: nil | H19: 0.52 | I19: 0 | J19: 1 | K19: 0 | L19: nil | M19: nil | N19: 0 | O19: 0 | P19: 0 | Q19: 1 | R19: D | S19: MPA
A20: adaptation_measures_climate_smart_agriculture_precision_agriculture | B20: 0.7 0.88 0.8 | C20: 12870472 | D20: 1 | E20: 0 | F20: 0 | G20: nil | H20: 0.55 | I20: 0 | J20: 1 | K20: 0 | L20: nil | M20: nil | N20: 0 | O20: 0 | P20: 0 | Q20: 1 | R20: D
A21: adaptation_measures_improvement_of_water_storage_systems | B21: 0.48 0.51 0.55 | C21: 21420000 | D21: 0.75 | E21: 0.75 | F21: 0 | G21: nil | H21: 0.45 | I21: 0 | J21: 1 | K21: 0 | L21: nil | M21: nil | N21: 0 | O21: 0 | P21: 0 | Q21: 1 | R21: D
A22: adaptation_measures_improvement_of_water_distribution_facilities | B22: 0.81 0.8 0.82 | C22: 105000000 | D22: 0.75 | E22: 0.75 | F22: 0 | G22: nil | H22: 0.47 | I22: 0 | J22: 1 | K22: 0 | L22: nil | M22: nil | N22: 0 | O22: 0 | P22: 0 | Q22: 1 | R22: D
A23: adaptation_measures_trees_planting | B23: 0.01 0.67 0.51 | C23: 69156293 | D23: 1 | E23: 0 | F23: 0 | G23: nil | H23: 0.35 | I23: 0 | J23: 1 | K23: 0 | L23: nil | M23: nil | N23: 0 | O23: 0 | P23: 0 | Q23: 1 | R23: FL | S23: TP
A24: adaptation_measures_retention_reservoirs | B24: 0.16 0.38 0.56 | C24: 10653600 | D24: 1 | E24: 0 | F24: 0 | G24: nil | H24: 0.85 | I24: 0 | J24: 1 | K24: 0 | L24: nil | M24: nil | N24: 0 | O24: 0 | P24: 0 | Q24: 1 | R24: FL | S24: RR
A25: adaptation_measures_dredging_of_canals | B25: 0.27 0.32 0.37 | C25: 40341171 | D25: 1 | E25: 0 | F25: 0 | G25: nil | H25: 0.6 | I25: 0 | J25: 1 | K25: 0 | L25: nil | M25: nil | N25: 0 | O25: 0 | P25: 0 | Q25: 1 | R25: FL | S25: DC
A26: adaptation_measures_infiltration_ponds | B26: 0.2 0.51 0.7 | C26: 52523956 | D26: 1 | E26: 0 | F26: 0 | G26: nil | H26: 0.52 | I26: 0 | J26: 1 | K26: 0 | L26: nil | M26: nil | N26: 0 | O26: 0 | P26: 0 | Q26: 1 | R26: FL | S26: IP
A27: adaptation_measures_recharging_wells | B27: 0.43 0.73 0.87 | C27: 77706469 | D27: 1 | E27: 0 | F27: 0 | G27: nil | H27: 0.35 | I27: 0 | J27: 1 | K27: 0 | L27: nil | M27: nil | N27: 0 | O27: 0 | P27: 0 | Q27: 1 | R27: FL | S27: RW
A28: adaptation_measures_small_dams | B28: 0.48 0.51 0.55 | C28: 1.6814806e+08 | D28: 1 | E28: 0 | F28: 0 | G28: nil | H28: 1e-05 | I28: 0 | J28: 1 | K28: 0 | L28: nil | M28: nil | N28: 0 | O28: 0 | P28: 0 | Q28: 1 | R28: FL | S28: SD
A29: adaptation_measures_early_warning_system | B29: 0.93 0.33 0.34 | C29: 459403.01 | D29: 1 | E29: 0 | F29: 0 | G29: nil | H29: 0.995 | I29: 0 | J29: 1 | K29: 0 | L29: nil | M29: nil | N29: 0 | O29: 0 | P29: 0 | Q29: 1 | R29: FL | S29: EWS
A30: adaptation_measures_wetland_restoration_and_rehabilitation | B30: 0.02 0.52 0.45 | C30: 3021000 | D30: 1 | E30: 0 | F30: 0 | G30: nil | H30: 0.98 | I30: 0 | J30: 1 | K30: 0 | L30: nil | M30: nil | N30: 0 | O30: 0 | P30: 0 | Q30: 1 | R30: FL
A31: adaptation_measures_improved_drainage_system | B31: 0.48 0.51 0.55 | C31: 21895244 | D31: 1 | E31: 0 | F31: 0 | G31: nil | H31: 0.97 | I31: 0 | J31: 1 | K31: 0 | L31: nil | M31: nil | N31: 0 | O31: 0 | P31: 0 | Q31: 1 | R31: FL
A32: adaptation_measures_training_for_agricultural_topic_for_adaptation | B32: 0.93 0.33 0.34 | C32: 1620000 | D32: 1 | E32: 0 | F32: 0 | G32: nil | H32: 0.989 | I32: 0 | J32: 1 | K32: 0 | L32: nil | M32: nil | N32: 0 | O32: 0 | P32: 0 | Q32: 1 | R32: FL
A33: adaptation_measures_retention_furrows | B33: 0.16 0.38 0.56 | C33: 30674921 | D33: 1 | E33: 0 | F33: 0 | G33: nil | H33: 0.9 | I33: 0 | J33: 1 | K33: 0 | L33: nil | M33: nil | N33: 0 | O33: 0 | P33: 0 | Q33: 1 | R33: FL | S33: RF
A34: adaptation_measures_agricultural_zoning | B34: 0.83 0.45 0.38 | C34: 13500000 | D34: 1 | E34: 0 | F34: 0 | G34: nil | H34: 0.973 | I34: 0 | J34: 1 | K34: 0 | L34: nil | M34: nil | N34: 0 | O34: 0 | P34: 0 | Q34: 1 | R34: FL | S34: AZ
A35: adaptation_measures_water_tolerant_crops | B35: 0.98 0.63 0.56 | C35: 13500000 | D35: 1 | E35: 0 | F35: 0 | G35: nil | H35: 0.98 | I35: 0 | J35: 1 | K35: 0 | L35: nil | M35: nil | N35: 0 | O35: 0 | P35: 0 | Q35: 1 | R35: FL | S35: WTC
A36: adaptation_measures_flood_index_insurance | B36: 1 0.75 0.6 | C36: 92345330 | D36: 1 | E36: 0 | F36: 0 | G36: nil | H36: 0.83 | I36: 0 | J36: 1 | K36: 0 | L36: nil | M36: nil | N36: 0 | O36: 0 | P36: 0 | Q36: 1 | R36: FL | S36: FI

Sheet discount
A1: year | B1: discount_rate
A2: 2000 | B2: 0.02
A3: 2001 | B3: 0.02
A4: 2002 | B4: 0.02
A5: 2003 | B5: 0.02
A6: 2004 | B6: 0.02
A7: 2005 | B7: 0.02
A8: 2006 | B8: 0.02
A9: 2007 | B9: 0.02
A10: 2008 | B10: 0.02
A11: 2009 | B11: 0.02
A12: 2010 | B12: 0.02
A13: 2011 | B13: 0.02
... A103: 2101 | B103: 0.02

Sheet _measures_details
A1: This sheet contains the detailed calculations for different measures (NOT READ BY CLIMADA)
A2: Note that all costs in sheet 'measures' need to be net present values 2012-2030 (reference 2012). Not all measures need to be based on the same discount rate etc.
A4: beach nourishment (see slides)
A6: width | B6: 22.86 | C6: m
A7: beach length | B7: 160934.4 | C7: m
A8: estimated depth | B8: 0.5 | C8: m
A9: volume | B9: =B6*B7*B8 | C9: m3
A11: costs per m3 | B11: 13.733482 | C11: $/m3
A13: initial costs | B13: =B9*B11 | C13: $
A14: replacement costs (every 6th year) | B14: =B13*0.25 | C14: $
A15: NPV | B15: =_discounting_sheet!D4 | C15: $
A18: elevate existing buildings
A19: we need to say elevate a certain percentage of existing buildings, each elevation costing a certain percentage of the reconstruction cost
A20: percentage elevated | B20: 0.5
A21: elevation cost per building | B21: 0.2 | C21: of building value
A22: elevation cost | B22: =B20*SUM(assets!#REF!)*_measures_details!B21 | C22: $
A24: vegetation management
A25: annual cost | B25: 4000000 | C25: $
A26: NPV | B26: =_discounting_sheet!F4 | C26: $
A28: sandbags
A29: sandbags need to be bought (incuding filling station) once, hence high initial cost, then maintenance and replacement plus an average labor cost for use
A30: initial acquisition | B30: 20000000 | C30: $
A31: maintenance | B31: 500000 | C31: $
A32: replacement | B32: 500000 | C32: $
A33: annual average manpower for usage | B33: 400000 | C33: $
A34: NPV | B34: =_discounting_sheet!H4 | C34: $
A36: seawall
A37: the seawall costs pr meter horizontal extent (construction once, maintanance ongoing) and per meter height
A38: height | B38: 3 | C38: m
A39: extent | B39: 30000 | C39: m
A40: building costs total | B40: =B38^2*B39*2000 | C40: $
A41: maintenance cost per | B41: 400 | C41: m
A42: maintenance costs | B42: =B39*B41 | C42: $
A43: NPV | B43: =_discounting_sheet!J4+B40 | C43: $

Sheet _discounting_sheet
A1: worksheet to discount measures (NOT READ BY CLIMADA)
A3: year | B3: yield | C3: beach nourishment | D3: discounted beach nourishment | E3: vegetation management | F3: discounted | G3: sandbagging | H3: discounted | I3: seawall | J3: discounted
A4: 2012 | B4: =discount!B14 | C4: 25262467 | D4: =C4+D5/(1+$B5) | E4: =_measures_details!$B$25 | F4: =E4+F5/(1+$B5) | G4: =_measures_details!$B$31+_measures_details!$B$32+_measures_details!$B$33 | H4: =G4+H5/(1+$B5) | I4: =_measures_details!$B$42 | J4: =I4+J5/(1+$B5)
A5: 2013 | B5: =discount!B15 | C5: 0 | D5: =C5+D6/(1+$B6) | E5: =_measures_details!$B$25 | F5: =E5+F6/(1+$B6) | G5: =_measures_details!$B$31+_measures_details!$B$32+_measures_details!$B$33 | H5: =G5+H6/(1+$B6) | I5: =_measures_details!$B$42 | J5: =I5+J6/(1+$B6)
A6: 2014 | B6: =discount!B16 | C6: 0 | D6: =C6+D7/(1+$B7) | E6: =_measures_details!$B$25 | F6: =E6+F7/(1+$B7) | G6: =_measures_details!$B$31+_measures_details!$B$32+_measures_details!$B$33 | H6: =G6+H7/(1+$B7) | I6: =_measures_details!$B$42 | J6: =I6+J7/(1+$B7)
A7: 2015 | B7: =discount!B17 | C7: 0 | D7: =C7+D8/(1+$B8) | E7: =_measures_details!$B$25 | F7: =E7+F8/(1+$B8) | G7: =_measures_details!$B$31+_measures_details!$B$32+_measures_details!$B$33 | H7: =G7+H8/(1+$B8) | I7: =_measures_details!$B$42 | J7: =I7+J8/(1+$B8)
A8: 2016 | B8: =discount!B18 | C8: 0 | D8: =C8+D9/(1+$B9) | E8: =_measures_details!$B$25 | F8: =E8+F9/(1+$B9) | G8: =_measures_details!$B$31+_measures_details!$B$32+_measures_details!$B$33 | H8: =G8+H9/(1+$B9) | I8: =_measures_details!$B$42 | J8: =I8+J9/(1+$B9)
A9: 2017 | B9: =discount!B19 | C9: 6315616.8 | D9: =C9+D10/(1+$B10) | E9: =_measures_details!$B$25 | F9: =E9+F10/(1+$B10) | G9: =_measures_details!$B$31+_measures_details!$B$32+_measures_details!$B$33 | H9: =G9+H10/(1+$B10) | I9: =_measures_details!$B$42 | J9: =I9+J10/(1+$B10)
A10: 2018 | B10: =discount!B20 | C10: 0 | D10: =C10+D11/(1+$B11) | E10: =_measures_details!$B$25 | F10: =E10+F11/(1+$B11) | G10: =_measures_details!$B$31+_measures_details!$B$32+_measures_details!$B$33 | H10: =G10+H11/(1+$B11) | I10: =_measures_details!$B$42 | J10: =I10+J11/(1+$B11)
A11: 2019 | B11: =discount!B21 | C11: 0 | D11: =C11+D12/(1+$B12) | E11: =_measures_details!$B$25 | F11: =E11+F12/(1+$B12) | G11: =_measures_details!$B$31+_measures_details!$B$32+_measures_details!$B$33 | H11: =G11+H12/(1+$B12) | I11: =_measures_details!$B$42 | J11: =I11+J12/(1+$B12)
A12: 2020 | B12: =discount!B22 | C12: 0 | D12: =C12+D13/(1+$B13) | E12: =_measures_details!$B$25 | F12: =E12+F13/(1+$B13) | G12: =_measures_details!$B$31+_measures_details!$B$32+_measures_details!$B$33 | H12: =G12+H13/(1+$B13) | I12: =_measures_details!$B$42 | J12: =I12+J13/(1+$B13)
A13: 2021 | B13: =discount!B23 | C13: 0 | D13: =C13+D14/(1+$B14) | E13: =_measures_details!$B$25 | F13: =E13+F14/(1+$B14) | G13: =_measures_details!$B$31+_measures_details!$B$32+_measures_details!$B$33 | H13: =G13+H14/(1+$B14) | I13: =_measures_details!$B$42 | J13: =I13+J14/(1+$B14)
A14: 2022 | B14: =discount!B24 | C14: 0 | D14: =C14+D15/(1+$B15) | E14: =_measures_details!$B$25 | F14: =E14+F15/(1+$B15) | G14: =_measures_details!$B$31+_measures_details!$B$32+_measures_details!$B$33 | H14: =G14+H15/(1+$B15) | I14: =_measures_details!$B$42 | J14: =I14+J15/(1+$B15)
A15: 2023 | B15: =discount!B25 | C15: 6315616.8 | D15: =C15+D16/(1+$B16) | E15: =_measures_details!$B$25 | F15: =E15+F16/(1+$B16) | G15: =_measures_details!$B$31+_measures_details!$B$32+_measures_details!$B$33 | H15: =G15+H16/(1+$B16) | I15: =_measures_details!$B$42 | J15: =I15+J16/(1+$B16)
... A21: 2029 | B21: =discount!B31 | C21: 6315616.8 | D21: =C21+D22/(1+$B22) | E21: =_measures_details!$B$25 | F21: =E21+F22/(1+$B22) | G21: =_measures_details!$B$31+_measures_details!$B$32+_measures_details!$B$33 | H21: =G21+H22/(1+$B22) | I21: =_measures_details!$B$42 | J21: =I21+J22/(1+$B22)
A22: 2030 | B22: =discount!B32 | C22: 0 | D22: =C22 | E22: =_measures_details!$B$25 | F22: =E22 | G22: =_measures_details!$B$31+_measures_details!$B$32+_measures_details!$B$33 | H22: =G22 | I22: =_measures_details!$B$42 | J22: =I22

Sheet names
A1: Item | B1: ID | C1: name
A2: Category_ID | B2: 1 | C2: Default category
A3: Region_ID | B3: 1 | C3: Default region
A4: reference_year | B4: 0 | C4: 2017
A5: DamageFunID | B5: 1 | C5: all default functions, based on expert judgement
A6: DamageFunID | B6: 3 | C6: demo damage function to reflect change in tropical cyclone (TC) buidling code, source expert judgement
A7: measureID | B7: 1 | C7: beach nourishment, demo
A8: measureID | B8: 2 | C8: vegetation management, demo
A9: measureID | B9: 3 | C9: sandbags, demo
A10: measureID | B10: 4 | C10: seawall, demo
A11: measureID | B11: 5 | C11: elevate existing buildings, demo
A12: measureID | B12: 6 | C12: enforce building code, demo, see DamageFunID 3
A13: measureID | B13: 7 | C13: risk transfer, demo
